amo_partner_crawler/__init__.py
amo_partner_crawler/core.py
amo_partner_crawler/exceptions.py
amo_partner_crawler/schemas.py
amo_partner_crawler/utils.py
amo_partner_crawler-2.1.3.dist-info/WHEEL
amo_partner_crawler-2.1.3.dist-info/METADATA
amo_partner_crawler-2.1.3.dist-info/RECORD
