Metadata-Version: 2.1
Name: amo-partner-crawler
Version: 2.1.3
Summary: SELENIUM CRAWLER FOR SCRAPING BILLING DATA FROM AMOCRM PARTNER CABINET
Author: Igor Romaschenko
Author-email: rocinantt@gmail.com
Requires-Python: >=3.8,<4.0
Classifier: Programming Language :: Python :: 3
Classifier: Programming Language :: Python :: 3.8
Classifier: Programming Language :: Python :: 3.9
Requires-Dist: datedelta (>=1.3,<2.0)
Requires-Dist: pydantic (>=1.8.1,<2.0.0)
Requires-Dist: selenium (>=3.141.0,<4.0.0)
